lynyrd/__about__.py
lynyrd/__init__.py
lynyrd/__main__.py
lynyrd-0.1.1.dist-info/METADATA
lynyrd-0.1.1.dist-info/WHEEL
lynyrd-0.1.1.dist-info/entry_points.txt
lynyrd-0.1.1.dist-info/licenses/LICENSE.txt
lynyrd-0.1.1.dist-info/RECORD
